bervr_messenger_client-2.1.4.data/scripts/client_run.py
client/__init__.py
client/client.py
client/client_run.py
client/client/__init__.py
client/client/add_contact.py
client/client/client_database.py
client/client/del_contact.py
client/client/main_window.py
client/client/main_window_conv.py
client/client/start_dialog.py
client/client/transport.py
client/common/__init__.py
client/common/decor.py
client/common/descriptors.py
client/common/errors.py
client/common/metaclasses.py
client/common/utils.py
client/common/variables.py
client/logs/__init__.py
client/logs/conf/__init__.py
client/logs/conf/client_log_config.py
bervr_messenger_client-2.1.4.dist-info/METADATA
bervr_messenger_client-2.1.4.dist-info/WHEEL
bervr_messenger_client-2.1.4.dist-info/top_level.txt
bervr_messenger_client-2.1.4.dist-info/RECORD
