Metadata-Version: 2.1
Name: bervr-messenger-client
Version: 2.1.4
Summary: A client part for messenger
Author: Aleksandr Filippov
Author-email: bervrr@gmail.com
Requires-Dist: PyQt5
Requires-Dist: SQLAlchemy
Requires-Dist: pycryptodome
Requires-Dist: pycryptodomex
Requires-Dist: chardet
